atol/__init__.py
atol/core.py
atol/exceptions.py
atol/models.py
atol/signals.py
atol/tasks.py
atol/utils.py
atol/views.py
atol/migrations/0001_initial.py
atol/migrations/0002_receipt_retried_at.py
atol/migrations/__init__.py
django_atol-1.4.1.dist-info/LICENSE
django_atol-1.4.1.dist-info/METADATA
django_atol-1.4.1.dist-info/WHEEL
django_atol-1.4.1.dist-info/top_level.txt
django_atol-1.4.1.dist-info/RECORD
