Metadata-Version: 2.1
Name: django-atol
Version: 1.4.1
Summary: Django integration with ATOL online
Home-page: https://github.com/MyBook/django-atol
Author: MyBook
Author-email: dev@mybook.ru
License: BSD
Keywords: atol
Classifier: Development Status :: 5 - Production/Stable
Classifier: Intended Audience :: Developers
Classifier: License :: OSI Approved :: BSD License
Classifier: Natural Language :: English
Classifier: Programming Language :: Python :: 3
Classifier: Programming Language :: Python :: 3.5
Classifier: Programming Language :: Python :: 3.6
License-File: LICENSE
Requires-Dist: requests (>=2.10.0)
Requires-Dist: python-dateutil (>=2.5.3)
Requires-Dist: django-model-utils (>=3.0.0)
Requires-Dist: celery (>=3.1.25)
Requires-Dist: shortuuid (>=1.0.1)
